bumblebee/__init__.py
bumblebee/keyboard.py
bumblebee/mouse.py
bumblebee/__pycache__/__init__.cpython-312.pyc
bumblebee/__pycache__/__init__.cpython-313.pyc
bumblebee/__pycache__/keyboard.cpython-312.pyc
bumblebee/__pycache__/keyboard.cpython-313.pyc
bumblebee/__pycache__/mouse.cpython-312.pyc
bumblebee/__pycache__/mouse.cpython-313.pyc
bumblebee/ai/__init__.py
bumblebee/ai/predict.py
bumblebee/ai/rnn.py
bumblebee/ai/__pycache__/__init__.cpython-312.pyc
bumblebee/ai/__pycache__/__init__.cpython-313.pyc
bumblebee/ai/__pycache__/predict.cpython-312.pyc
bumblebee/ai/__pycache__/predict.cpython-313.pyc
bumblebee/ai/__pycache__/rnn.cpython-312.pyc
bumblebee/ai/__pycache__/rnn.cpython-313.pyc
bumblebee/ai/models/README.md
bumblebee/ai/models/bumblebee-c-v1.pth
the_bumblebee-1.0.2.dist-info/LICENSE.md
the_bumblebee-1.0.2.dist-info/METADATA
the_bumblebee-1.0.2.dist-info/WHEEL
the_bumblebee-1.0.2.dist-info/top_level.txt
the_bumblebee-1.0.2.dist-info/RECORD
