Metadata-Version: 2.2
Name: the-bumblebee
Version: 1.0.2
Summary: An AI-powered Python package for natural, human-like mouse and keyboard control.
Home-page: https://github.com/socioy/bumblebee
Author: socioy
Author-email: bumblebee@socioy.com
Classifier: Programming Language :: Python :: 3
Classifier: Programming Language :: Python :: 3.12
Classifier: Operating System :: OS Independent
Classifier: License :: OSI Approved :: MIT License
Requires-Python: >=3.11
License-File: LICENSE.md
Requires-Dist: numpy>=2.2.4
Requires-Dist: torch>=2.6.0
Requires-Dist: scipy>=1.15.2
Requires-Dist: pynput>=1.8.1
Requires-Dist: PyAutoGUI>=0.9.54
Dynamic: author
Dynamic: author-email
Dynamic: classifier
Dynamic: description
Dynamic: description-content-type
Dynamic: home-page
Dynamic: requires-dist
Dynamic: requires-python
Dynamic: summary
